utcp_text/__init__.py
utcp_text/text_call_template.py
utcp_text/text_communication_protocol.py
utcp_text-1.0.3.dist-info/METADATA
utcp_text-1.0.3.dist-info/WHEEL
utcp_text-1.0.3.dist-info/entry_points.txt
utcp_text-1.0.3.dist-info/top_level.txt
utcp_text-1.0.3.dist-info/RECORD
